func_live/__init__.py
func_live/config.py
func_live/recursively_upload_filepaths.py
func_live/upload_file.py
func_live-1.2.26.dist-info/METADATA
func_live-1.2.26.dist-info/WHEEL
func_live-1.2.26.dist-info/top_level.txt
func_live-1.2.26.dist-info/RECORD
