Metadata-Version: 2.1
Name: func_live
Version: 1.2.26
Summary: Allows you to import and call the functions on www.func.live
Home-page: https://func.live
Author: Aravind Vakil
License: ISC
Keywords: func.live func functions
Requires-Dist: aiohttp
Requires-Dist: requests
Requires-Dist: httpx
